distributions/Binomialdistribution.py
distributions/Gaussiandistribution.py
distributions/Generaldistribution.py
distributions/__init__.py
elementary_probability_distributions-0.1.dist-info/DESCRIPTION.rst
elementary_probability_distributions-0.1.dist-info/METADATA
elementary_probability_distributions-0.1.dist-info/RECORD
elementary_probability_distributions-0.1.dist-info/WHEEL
elementary_probability_distributions-0.1.dist-info/metadata.json
elementary_probability_distributions-0.1.dist-info/top_level.txt
